odoo/addons/sale_order_line_date_propagate/LICENSE
odoo/addons/sale_order_line_date_propagate/README.rst
odoo/addons/sale_order_line_date_propagate/__init__.py
odoo/addons/sale_order_line_date_propagate/__manifest__.py
odoo/addons/sale_order_line_date_propagate/images/screen.png
odoo/addons/sale_order_line_date_propagate/models/__init__.py
odoo/addons/sale_order_line_date_propagate/models/sale_order.py
odoo/addons/sale_order_line_date_propagate/models/sale_order_line.py
odoo/addons/sale_order_line_date_propagate/static/description/icon.png
odoo/addons/sale_order_line_date_propagate/static/description/index.html
odoo/addons/sale_order_line_date_propagate/tests/TEST_INSTRUCTIONS.rst
odoo_addon_sale_order_line_date_propagate-16.0.1.0.0.dist-info/METADATA
odoo_addon_sale_order_line_date_propagate-16.0.1.0.0.dist-info/WHEEL
odoo_addon_sale_order_line_date_propagate-16.0.1.0.0.dist-info/top_level.txt
odoo_addon_sale_order_line_date_propagate-16.0.1.0.0.dist-info/RECORD
